{
  "__data_type": "UTI ",
  "AddCost": {
    "type": "dword",
    "value": 0
  },
  "BaseItem": {
    "type": "int",
    "value": 19
  },
  "Charges": {
    "type": "byte",
    "value": 0
  },
  "Comment": {
    "type": "cexostring",
    "value": "1"
  },
  "Cost": {
    "type": "dword",
    "value": 169
  },
  "Cursed": {
    "type": "byte",
    "value": 0
  },
  "DescIdentified": {
    "id": 3732,
    "type": "cexolocstring",
    "value": {
      "0": ""
    }
  },
  "Description": {
    "type": "cexolocstring",
    "value": {
      "0": ""
    }
  },
  "Identified": {
    "type": "byte",
    "value": 0
  },
  "LocalizedName": {
    "id": 13409,
    "type": "cexolocstring",
    "value": {
      "0": "Store Bought Prayer Beads"
    }
  },
  "ModelPart1": {
    "type": "byte",
    "value": 9
  },
  "PaletteID": {
    "type": "byte",
    "value": 21
  },
  "Plot": {
    "type": "byte",
    "value": 0
  },
  "PropertiesList": {
    "type": "list",
    "value": [
      {
        "__struct_id": 0,
        "ChanceAppear": {
          "type": "byte",
          "value": 100
        },
        "CostTable": {
          "type": "byte",
          "value": 3
        },
        "CostValue": {
          "type": "word",
          "value": 2
        },
        "Param1": {
          "type": "byte",
          "value": 255
        },
        "Param1Value": {
          "type": "byte",
          "value": 0
        },
        "PropertyName": {
          "type": "word",
          "value": 15
        },
        "Subtype": {
          "type": "word",
          "value": 278
        }
      }
    ]
  },
  "StackSize": {
    "type": "word",
    "value": 1
  },
  "Stolen": {
    "type": "byte",
    "value": 0
  },
  "Tag": {
    "type": "cexostring",
    "value": "000_advprov_019"
  },
  "TemplateResRef": {
    "type": "resref",
    "value": "000_advprov_019"
  }
}
